plico_motor/__init__.py
plico_motor/__version__.py
plico_motor/client/__init__.py
plico_motor/client/abstract_motor_client.py
plico_motor/client/motor_client.py
plico_motor/client/simulated_motor_client.py
plico_motor/client/snapshot_entry.py
plico_motor/gui/__init__.py
plico_motor/gui/motor_control_gui.py
plico_motor/gui/plico_motor_gui.py
plico_motor/types/__init__.py
plico_motor/types/motor_status.py
plico_motor/utils/__init__.py
plico_motor/utils/constants.py
plico_motor/utils/timeout.py
plico_motor-0.0.5.dist-info/LICENSE
plico_motor-0.0.5.dist-info/METADATA
plico_motor-0.0.5.dist-info/WHEEL
plico_motor-0.0.5.dist-info/entry_points.txt
plico_motor-0.0.5.dist-info/top_level.txt
plico_motor-0.0.5.dist-info/RECORD
