Metadata-Version: 2.1
Name: plico_motor
Version: 0.0.5
Summary: motor controller with PLICO
Home-page: https://github.com/ArcetriAdaptiveOptics/plico_motor
Author: Lorenzo Busoni, Alfio Puglisi
Author-email: lorenzo.busoni@inaf.it
License: MIT
Keywords: plico,motor,picomotor,laboratory,instrumentation control
Classifier: Development Status :: 4 - Beta
Classifier: Operating System :: POSIX :: Linux
Classifier: Programming Language :: Python :: 3
License-File: LICENSE
Requires-Dist: plico >=0.18
Requires-Dist: numpy
Requires-Dist: guietta
